odoo10_addon_l10n_es_account_asset-10.0.1.0.3-py2.7-nspkg.pth
odoo/addons/l10n_es_account_asset/README.rst
odoo/addons/l10n_es_account_asset/__init__.py
odoo/addons/l10n_es_account_asset/__manifest__.py
odoo/addons/l10n_es_account_asset/i18n/ca.po
odoo/addons/l10n_es_account_asset/i18n/cs.po
odoo/addons/l10n_es_account_asset/i18n/de.po
odoo/addons/l10n_es_account_asset/i18n/es.po
odoo/addons/l10n_es_account_asset/i18n/es_CO.po
odoo/addons/l10n_es_account_asset/i18n/es_ES.po
odoo/addons/l10n_es_account_asset/i18n/fr.po
odoo/addons/l10n_es_account_asset/i18n/fr_BE.po
odoo/addons/l10n_es_account_asset/i18n/gl.po
odoo/addons/l10n_es_account_asset/i18n/hr.po
odoo/addons/l10n_es_account_asset/i18n/pl.po
odoo/addons/l10n_es_account_asset/i18n/pt.po
odoo/addons/l10n_es_account_asset/i18n/pt_BR.po
odoo/addons/l10n_es_account_asset/i18n/ru.po
odoo/addons/l10n_es_account_asset/i18n/sl.po
odoo/addons/l10n_es_account_asset/i18n/sv.po
odoo/addons/l10n_es_account_asset/i18n/vi.po
odoo/addons/l10n_es_account_asset/models/__init__.py
odoo/addons/l10n_es_account_asset/models/account_asset.py
odoo/addons/l10n_es_account_asset/static/description/icon.png
odoo/addons/l10n_es_account_asset/tests/__init__.py
odoo/addons/l10n_es_account_asset/tests/test_l10n_es_account_asset.py
odoo/addons/l10n_es_account_asset/views/account_asset_view.xml
odoo10_addon_l10n_es_account_asset-10.0.1.0.3.dist-info/DESCRIPTION.rst
odoo10_addon_l10n_es_account_asset-10.0.1.0.3.dist-info/METADATA
odoo10_addon_l10n_es_account_asset-10.0.1.0.3.dist-info/RECORD
odoo10_addon_l10n_es_account_asset-10.0.1.0.3.dist-info/WHEEL
odoo10_addon_l10n_es_account_asset-10.0.1.0.3.dist-info/metadata.json
odoo10_addon_l10n_es_account_asset-10.0.1.0.3.dist-info/namespace_packages.txt
odoo10_addon_l10n_es_account_asset-10.0.1.0.3.dist-info/top_level.txt
